<annotation verified="no">
  <folder>train</folder>
  <filename>wdj1</filename>
  <path>/home/wj/study/dlearn/02-CSDN/data/TFRecord_make/train/wdj1.jpeg</path>
  <source>
    <database>Unknown</database>
  </source>
  <size>
    <width>300</width>
    <height>168</height>
    <depth>3</depth>
  </size>
  <segmented>0</segmented>
  <object>
    <name>wdj</name>
    <pose>Unspecified</pose>
    <truncated>0</truncated>
    <Difficult>0</Difficult>
    <bndbox>
      <xmin>100</xmin>
      <ymin>14</ymin>
      <xmax>149</xmax>
      <ymax>63</ymax>
    </bndbox>
  </object>
</annotation>
